gameart/FileHandler.py
gameart/__init__.py
gameart/__main__.py
gameart/api.py
gameart/cli.py
gameart/gui.py
gameart/draw/__init__.py
gameart/draw/art.py
gameart/inputs/__init__.py
gameart/inputs/mousetracker.py
gameart/utils/__init__.py
gameart/utils/utils.py
gameart-0.1.27.dist-info/LICENSE
gameart-0.1.27.dist-info/METADATA
gameart-0.1.27.dist-info/WHEEL
gameart-0.1.27.dist-info/entry_points.txt
gameart-0.1.27.dist-info/top_level.txt
gameart-0.1.27.dist-info/RECORD
