Metadata-Version: 2.1
Name: gameart
Version: 0.1.27
Summary: Create printable art with the movement of your mouse.
Author-email: Andreas Schneider <andmangames@gmail.com>
Project-URL: Repository, https://github.com/AndManGames/GameArt
Project-URL: Bug Tracker, https://github.com/AndManGames/GameArt/issues
Classifier: Programming Language :: Python :: 3
Classifier: Programming Language :: Python :: 3.10
Classifier: Programming Language :: Python :: 3.11
Classifier: Programming Language :: Python :: 3.12
Classifier: Operating System :: OS Independent
Requires-Python: >=3.10
License-File: LICENSE
Requires-Dist: matplotlib >=3.8.0
Requires-Dist: pandas >=2.1.1
Requires-Dist: fire >=0.5.0
Requires-Dist: pynput >=1.7.6
Requires-Dist: PyQt5 >=5.15.10
Provides-Extra: dev
Requires-Dist: pytest >=7.4.2 ; extra == 'dev'
Requires-Dist: pre-commit >=3.5.0 ; extra == 'dev'
Provides-Extra: release
Requires-Dist: build >=1.0.3 ; extra == 'release'
